{"companyName":"novica","address":"novica","contactPhone":"novica","userName":"novica","password":"novica","suspended":false}
{"companyName":"novicapravi","address":"novica.tepic@student.etf.unibl.org","contactPhone":"novicapravi","userName":"novicapravi","password":"novicapravi","suspended":false}
{"companyName":"marko","address":"marko","contactPhone":"marko","userName":"marko","password":"marko","suspended":true}
{"companyName":"123","address":"123","contactPhone":"123","userName":"123","password":"123","suspended":false}

